pypilearnt/__init__.py
pypilearnt/cli.py
pypilearnt/pypilearnt.py
pypilearnt-0.1.5.dist-info/DESCRIPTION.rst
pypilearnt-0.1.5.dist-info/METADATA
pypilearnt-0.1.5.dist-info/RECORD
pypilearnt-0.1.5.dist-info/WHEEL
pypilearnt-0.1.5.dist-info/entry_points.txt
pypilearnt-0.1.5.dist-info/metadata.json
pypilearnt-0.1.5.dist-info/top_level.txt
