Metadata-Version: 2.0
Name: pypilearnt
Version: 0.1.5
Summary: just learn how to upload project to pypi
Home-page: https://github.com/ficapy/pypilearnt
Author: pypilearnt
Author-email: c4d@outlook.com
License: GNU General Public License v3
Keywords: pypilearnt
Platform: UNKNOWN
Classifier: Development Status :: 2 - Pre-Alpha
Classifier: Intended Audience :: Developers
Classifier: License :: OSI Approved :: GNU General Public License (GPL)
Classifier: Natural Language :: English
Classifier: Programming Language :: Python :: 2
Classifier: Programming Language :: Python :: 2.6
Classifier: Programming Language :: Python :: 2.7
Classifier: Programming Language :: Python :: 3
Classifier: Programming Language :: Python :: 3.3
Classifier: Programming Language :: Python :: 3.4
Classifier: Programming Language :: Python :: 3.5
Requires-Dist: Click (>=6.0)
